hostsresolver/__init__.py
hostsresolver/cache.py
hostsresolver/hostsfile_source.py
hostsresolver/vagrant_hostmanager_source.py
hostsresolver/vagrant_source.py
python_hostsresolver-0.0.1.dist-info/DESCRIPTION.rst
python_hostsresolver-0.0.1.dist-info/METADATA
python_hostsresolver-0.0.1.dist-info/RECORD
python_hostsresolver-0.0.1.dist-info/WHEEL
python_hostsresolver-0.0.1.dist-info/metadata.json
python_hostsresolver-0.0.1.dist-info/pbr.json
python_hostsresolver-0.0.1.dist-info/top_level.txt
