Metadata-Version: 2.0
Name: python-hostsresolver
Version: 0.0.1
Summary: Translate ephemeral virtual machines names into IP addresses for python projects without requiring
Requires-Dist: python-vagrant
